{
    "-1003771460278": {
        "8037987056": {
            "owner": "6085551760",
            "ownername": "J-Satchmo",
            "price": 125,
            "nickname": "una Z",
            "history": [
                {
                    "from": "系统",
                    "to": "J-Satchmo",
                    "to_id": "6085551760",
                    "price": 100,
                    "time": "2026-02-23 20:59:28"
                }
            ]
        },
        "6085551760": {
            "owner": "8037987056",
            "ownername": "una Z",
            "price": 125,
            "nickname": "J-Satchmo",
            "history": [
                {
                    "from": "系统",
                    "to": "una Z",
                    "to_id": "8037987056",
                    "price": 100,
                    "time": "2026-02-27 23:48:32"
                }
            ]
        }
    },
    "-1003648060909": {
        "6247279560": {
            "owner": "997916840",
            "ownername": "牢大（已重生）",
            "price": 156,
            "nickname": "梦 群招商【代开会员/NFT/礼物888租售/飞机号】",
            "history": [
                {
                    "from": "系统",
                    "to": "J-Satchmo",
                    "to_id": "6085551760",
                    "price": 100,
                    "time": "2026-03-01 14:00:07"
                },
                {
                    "from": "J-Satchmo",
                    "to": "牢大（已重生）",
                    "to_id": "997916840",
                    "price": 125,
                    "time": "2026-03-08 11:58:03"
                }
            ]
        },
        "7176715028": {
            "owner": "7579217346",
            "ownername": "将军担保宣传员·小淡",
            "price": 125,
            "nickname": "蛋蛋（广告位招商）",
            "history": [
                {
                    "from": "系统",
                    "to": "将军担保宣传员·小淡",
                    "to_id": "7579217346",
                    "price": 100,
                    "time": "2026-03-01 14:20:48"
                }
            ]
        },
        "7579217346": {
            "owner": "6085551760",
            "ownername": "J-Satchmo",
            "price": 125,
            "nickname": "将军担保宣传员·小淡",
            "history": [
                {
                    "from": "系统",
                    "to": "J-Satchmo",
                    "to_id": "6085551760",
                    "price": 100,
                    "time": "2026-03-01 14:21:23"
                }
            ]
        },
        "7632577754": {
            "owner": "6593929746",
            "ownername": "瑶儿🌸",
            "price": 195,
            "nickname": "小雅",
            "history": [
                {
                    "from": "系统",
                    "to": "J-Satchmo",
                    "to_id": "6085551760",
                    "price": 100,
                    "time": "2026-03-07 00:04:54"
                },
                {
                    "from": "J-Satchmo",
                    "to": "牢大（已重生）",
                    "to_id": "997916840",
                    "price": 125,
                    "time": "2026-03-08 09:57:54"
                },
                {
                    "from": "牢大（已重生）",
                    "to": "瑶儿🌸",
                    "to_id": "6593929746",
                    "price": 156,
                    "time": "2026-03-09 00:50:30"
                }
            ]
        },
        "6593929746": {
            "owner": "7364509926",
            "ownername": "阿龙-老K",
            "price": 303,
            "nickname": "瑶儿🌸",
            "history": [
                {
                    "from": "系统",
                    "to": "J-Satchmo",
                    "to_id": "6085551760",
                    "price": 100,
                    "time": "2026-03-08 09:47:44"
                },
                {
                    "from": "J-Satchmo",
                    "to": "小呆",
                    "to_id": "7527220569",
                    "price": 125,
                    "time": "2026-03-08 10:00:21"
                },
                {
                    "from": "小呆",
                    "to": "牢大（已重生）",
                    "to_id": "997916840",
                    "price": 156,
                    "time": "2026-03-08 10:03:09"
                },
                {
                    "from": "牢大（已重生）",
                    "to": "阿龙-老K",
                    "to_id": "7364509926",
                    "price": 195,
                    "time": "2026-03-09 04:19:38"
                },
                {
                    "from": "无主",
                    "to": "阿龙-老K",
                    "to_id": "7364509926",
                    "price": 243,
                    "time": "2026-03-10 04:17:55"
                }
            ]
        },
        "6085551760": {
            "owner": "997916840",
            "ownername": "牢大（已重生）",
            "price": 243,
            "nickname": "J-Satchmo",
            "history": [
                {
                    "from": "系统",
                    "to": "瑶儿🌸",
                    "to_id": "6593929746",
                    "price": 100,
                    "time": "2026-03-08 09:49:26"
                },
                {
                    "from": "瑶儿🌸",
                    "to": "牢大（已重生）",
                    "to_id": "997916840",
                    "price": 125,
                    "time": "2026-03-08 09:50:36"
                },
                {
                    "from": "牢大（已重生）",
                    "to": "小呆",
                    "to_id": "7527220569",
                    "price": 156,
                    "time": "2026-03-08 09:54:13"
                },
                {
                    "from": "无主",
                    "to": "牢大（已重生）",
                    "to_id": "997916840",
                    "price": 195,
                    "time": "2026-03-08 10:05:31"
                }
            ]
        },
        "997916840": {
            "owner": "7527220569",
            "ownername": "小呆",
            "price": 156,
            "nickname": "牢大（已重生）",
            "history": [
                {
                    "from": "系统",
                    "to": "J-Satchmo",
                    "to_id": "6085551760",
                    "price": 100,
                    "time": "2026-03-08 09:50:17"
                },
                {
                    "from": "J-Satchmo",
                    "to": "小呆",
                    "to_id": "7527220569",
                    "price": 125,
                    "time": "2026-03-08 09:50:19"
                }
            ]
        },
        "7527220569": {
            "owner": "6593929746",
            "ownername": "瑶儿🌸",
            "price": 156,
            "nickname": "小呆",
            "history": [
                {
                    "from": "系统",
                    "to": "牢大（已重生）",
                    "to_id": "997916840",
                    "price": 100,
                    "time": "2026-03-08 09:54:22"
                },
                {
                    "from": "无主",
                    "to": "瑶儿🌸",
                    "to_id": "6593929746",
                    "price": 125,
                    "time": "2026-03-08 10:09:46"
                }
            ]
        },
        "7990282654": {
            "owner": "997916840",
            "ownername": "牢大（已重生）",
            "price": 125,
            "nickname": "神宝",
            "history": [
                {
                    "from": "系统",
                    "to": "牢大（已重生）",
                    "to_id": "997916840",
                    "price": 100,
                    "time": "2026-03-08 10:14:40"
                }
            ]
        },
        "7081935760": {
            "owner": "6593929746",
            "ownername": "瑶儿🌸",
            "price": 125,
            "nickname": "੭ ᩚ 八方",
            "history": [
                {
                    "from": "系统",
                    "to": "瑶儿🌸",
                    "to_id": "6593929746",
                    "price": 100,
                    "time": "2026-03-08 22:06:00"
                }
            ]
        },
        "7364509926": {
            "owner": "997916840",
            "ownername": "牢大（已重生）",
            "price": 243,
            "nickname": "阿龙-老K",
            "history": [
                {
                    "from": "系统",
                    "to": "瑶儿🌸",
                    "to_id": "6593929746",
                    "price": 100,
                    "time": "2026-03-08 22:08:13"
                },
                {
                    "from": "无主",
                    "to": "小呆",
                    "to_id": "7527220569",
                    "price": 125,
                    "time": "2026-03-08 22:12:12"
                },
                {
                    "from": "小呆",
                    "to": "瑶儿🌸",
                    "to_id": "6593929746",
                    "price": 156,
                    "time": "2026-03-08 22:13:09"
                },
                {
                    "from": "无主",
                    "to": "牢大（已重生）",
                    "to_id": "997916840",
                    "price": 195,
                    "time": "2026-03-09 18:55:36"
                }
            ]
        },
        "8033034578": {
            "owner": "7364509926",
            "ownername": "阿龙-老K",
            "price": 125,
            "nickname": "如烟出海，全球海外号商借钱请裸聊确定",
            "history": [
                {
                    "from": "系统",
                    "to": "阿龙-老K",
                    "to_id": "7364509926",
                    "price": 100,
                    "time": "2026-03-08 23:23:00"
                }
            ]
        },
        "6888384284": {
            "owner": "7364509926",
            "ownername": "阿龙-老K",
            "price": 125,
            "nickname": "小姨子",
            "history": [
                {
                    "from": "系统",
                    "to": "阿龙-老K",
                    "to_id": "7364509926",
                    "price": 100,
                    "time": "2026-03-09 00:36:04"
                }
            ]
        }
    },
    "-1003266766385": {
        "6522921593": {
            "owner": "6085551760",
            "ownername": "J-Satchmo",
            "price": 125,
            "nickname": "Kiss",
            "history": [
                {
                    "from": "系统",
                    "to": "J-Satchmo",
                    "to_id": "6085551760",
                    "price": 100,
                    "time": "2026-03-06 10:51:12"
                }
            ]
        },
        "8187270541": {
            "owner": "6085551760",
            "ownername": "J-Satchmo",
            "price": 125,
            "nickname": "小五",
            "history": [
                {
                    "from": "系统",
                    "to": "J-Satchmo",
                    "to_id": "6085551760",
                    "price": 100,
                    "time": "2026-03-08 13:00:46"
                }
            ]
        }
    },
    "-1003755482356": {
        "5637548469": {
            "owner": "6888384284",
            "ownername": "小姨子",
            "price": 195,
            "nickname": "沈明i（关于资金裸聊确认）",
            "history": [
                {
                    "from": "系统",
                    "to": "小姨子",
                    "to_id": "6888384284",
                    "price": 100,
                    "time": "2026-03-09 00:36:53"
                },
                {
                    "from": "小姨子",
                    "to": "苘",
                    "to_id": "7820306932",
                    "price": 125,
                    "time": "2026-03-09 01:16:04"
                },
                {
                    "from": "苘",
                    "to": "小姨子",
                    "to_id": "6888384284",
                    "price": 156,
                    "time": "2026-03-09 04:43:10"
                }
            ]
        },
        "6888384284": {
            "owner": "7820306932",
            "ownername": "苘",
            "price": 378,
            "nickname": "小姨子",
            "history": [
                {
                    "from": "系统",
                    "to": "苘",
                    "to_id": "7820306932",
                    "price": 100,
                    "time": "2026-03-09 00:40:28"
                },
                {
                    "from": "苘",
                    "to": "往事 随风",
                    "to_id": "7992687169",
                    "price": 125,
                    "time": "2026-03-09 01:18:39"
                },
                {
                    "from": "往事 随风",
                    "to": "沈明i（关于资金裸聊确认）",
                    "to_id": "5637548469",
                    "price": 156,
                    "time": "2026-03-09 01:24:57"
                },
                {
                    "from": "无主",
                    "to": "苘",
                    "to_id": "7820306932",
                    "price": 195,
                    "time": "2026-03-09 21:05:03"
                },
                {
                    "from": "苘",
                    "to": "熊",
                    "to_id": "8173530865",
                    "price": 243,
                    "time": "2026-03-09 21:05:09"
                },
                {
                    "from": "熊",
                    "to": "苘",
                    "to_id": "7820306932",
                    "price": 303,
                    "time": "2026-03-10 02:56:48"
                }
            ]
        },
        "7820306932": {
            "owner": null,
            "ownername": "无主",
            "price": 125,
            "nickname": "苘",
            "history": [
                {
                    "from": "系统",
                    "to": "小姨子",
                    "to_id": "6888384284",
                    "price": 100,
                    "time": "2026-03-09 01:16:23"
                }
            ]
        },
        "7992687169": {
            "owner": "6888384284",
            "ownername": "小姨子",
            "price": 156,
            "nickname": "往事 随风",
            "history": [
                {
                    "from": "系统",
                    "to": "沈明i（关于资金裸聊确认）",
                    "to_id": "5637548469",
                    "price": 100,
                    "time": "2026-03-09 01:18:05"
                },
                {
                    "from": "沈明i（关于资金裸聊确认）",
                    "to": "小姨子",
                    "to_id": "6888384284",
                    "price": 125,
                    "time": "2026-03-10 00:14:49"
                }
            ]
        },
        "8266221209": {
            "owner": "8173530865",
            "ownername": "熊",
            "price": 156,
            "nickname": "馨月",
            "history": [
                {
                    "from": "系统",
                    "to": "往事 随风",
                    "to_id": "7992687169",
                    "price": 100,
                    "time": "2026-03-09 07:46:42"
                },
                {
                    "from": "往事 随风",
                    "to": "熊",
                    "to_id": "8173530865",
                    "price": 125,
                    "time": "2026-03-09 07:47:03"
                }
            ]
        },
        "7632577754": {
            "owner": "7992687169",
            "ownername": "往事 随风",
            "price": 125,
            "nickname": "小雅",
            "history": [
                {
                    "from": "系统",
                    "to": "往事 随风",
                    "to_id": "7992687169",
                    "price": 100,
                    "time": "2026-03-09 21:21:06"
                }
            ]
        }
    }
}