{
  "6085551760": {
    "full_name": "J-Satchmo",
    "username": "nuan12",
    "username_history": [],
    "last_seen": 1771509816
  },
  "7011142710": {
    "full_name": "小美",
    "username": "ldd147852",
    "username_history": [],
    "last_seen": 1770649412
  },
  "6470055452": {
    "full_name": "Js",
    "username": "Js_2580",
    "username_history": [],
    "last_seen": 1771525006
  },
  "8123837039": {
    "full_name": "心事全在脸上",
    "username": "ok898888",
    "username_history": [
      "io731"
    ],
    "last_seen": 1771414817
  },
  "7771272769": {
    "full_name": "王 🫅",
    "username": "Excel33333",
    "username_history": [],
    "last_seen": 1770391399
  },
  "8187496085": {
    "full_name": "威",
    "username": "ok5834",
    "username_history": [],
    "last_seen": 1771514091
  },
  "8058367547": {
    "full_name": "晨 sir",
    "username": "chensir998998",
    "username_history": [],
    "last_seen": 1770392879
  },
  "8380029499": {
    "full_name": "诗酒（流年伏吟金水通关）",
    "username": "ylll02",
    "username_history": [],
    "last_seen": 1771560978
  },
  "8185397416": {
    "full_name": "",
    "username": null,
    "username_history": [
      "UB_NaNa"
    ],
    "last_seen": 1770990215
  },
  "8200325391": {
    "full_name": "白小姐 (Shuffle)",
    "username": "MissBai7",
    "username_history": [],
    "last_seen": 1770900734
  },
  "5988487422": {
    "full_name": "季伯端（西港到付电子烟🧊k水可乐麻古）招中间商",
    "username": "jiboduan1",
    "username_history": [],
    "last_seen": 1770922419
  },
  "8267928786": {
    "full_name": "野原 新之助",
    "username": "CNYdd",
    "username_history": [],
    "last_seen": 1770415284
  },
  "1672744771": {
    "full_name": "夏凯",
    "username": "bckyxk",
    "username_history": [],
    "last_seen": 1771491989
  },
  "5105046153": {
    "full_name": "凯恩.",
    "username": "V555555555555555555555",
    "username_history": [],
    "last_seen": 1771566689
  },
  "5800111202": {
    "full_name": "蛮丶蛮",
    "username": "man748748",
    "username_history": [],
    "last_seen": 1771498703
  },
  "6429420628": {
    "full_name": "阳阳",
    "username": "yang6186188",
    "username_history": [],
    "last_seen": 1771410843
  },
  "6956943076": {
    "full_name": "波贝直招(原南海酒店)不禁足-（快杀）",
    "username": "Tudou1125",
    "username_history": [],
    "last_seen": 1771558666
  },
  "8252065503": {
    "full_name": "Matthew Ross",
    "username": "Arracacha_chankings",
    "username_history": [],
    "last_seen": 1770453756
  },
  "8237809215": {
    "full_name": "Heather Benson",
    "username": "corkeroverfallen",
    "username_history": [],
    "last_seen": 1770449622
  },
  "8264954003": {
    "full_name": "Richard Harrisfield",
    "username": "mirbaneZapateo",
    "username_history": [],
    "last_seen": 1770459919
  },
  "8520760791": {
    "full_name": "Patrick Brown",
    "username": "dotes_improve",
    "username_history": [],
    "last_seen": 1770454900
  },
  "7145022233": {
    "full_name": "村 长",
    "username": "jujidi99",
    "username_history": [],
    "last_seen": 1771047221
  },
  "5575250927": {
    "full_name": "嘿！",
    "username": "ok112299",
    "username_history": [],
    "last_seen": 1770883105
  },
  "6696797434": {
    "full_name": "北",
    "username": "Beibb8888",
    "username_history": [],
    "last_seen": 1770662260
  },
  "8111781344": {
    "full_name": "我真的很无语",
    "username": "jierui0008",
    "username_history": [],
    "last_seen": 1771495805
  },
  "7467050292": {
    "full_name": "初衷✨迪柬现货男女装包包饰品手表",
    "username": "jiuaq11",
    "username_history": [],
    "last_seen": 1771491490
  },
  "6943349903": {
    "full_name": "串串香（不卖串）",
    "username": "wocaonimq",
    "username_history": [],
    "last_seen": 1771049885
  },
  "7307387766": {
    "full_name": "酸菜🫥（泰国居家办公3个月免赔）",
    "username": "hellosuancai",
    "username_history": [],
    "last_seen": 1771513622
  },
  "5046594501": {
    "full_name": "💲",
    "username": "cccccchong99",
    "username_history": [],
    "last_seen": 1770649499
  },
  "8159435132": {
    "full_name": "优币娱乐城 官方推广 天宝",
    "username": "SH11003",
    "username_history": [],
    "last_seen": 1770535627
  },
  "8019410677": {
    "full_name": "Sunny °",
    "username": "Sunny1058",
    "username_history": [],
    "last_seen": 1770896670
  },
  "7699913200": {
    "full_name": "无敌-曼谷市区直招（非脖系）",
    "username": "WD731",
    "username_history": [],
    "last_seen": 1771410938
  },
  "6889105013": {
    "full_name": "【天宝集团】体育盘总监直招💋",
    "username": "HR_ale521",
    "username_history": [],
    "last_seen": 1771568240
  },
  "8432100138": {
    "full_name": "Ralph2402 Ortiz",
    "username": "Abrasiometergothish",
    "username_history": [],
    "last_seen": 1770470501
  },
  "5231217128": {
    "full_name": "迪拜，震动棒 跳蛋 飞机杯 果冻 伟哥 倒膜娃娃 情趣内衣👙",
    "username": "woshidibai992",
    "username_history": [],
    "last_seen": 1771545365
  },
  "6765569242": {
    "full_name": "阿正",
    "username": "azheng_886",
    "username_history": [],
    "last_seen": 1770819722
  },
  "8187270541": {
    "full_name": "小五",
    "username": "xiaowuya007",
    "username_history": [],
    "last_seen": 1771506385
  },
  "7597233169": {
    "full_name": "Nf6",
    "username": "Nf680",
    "username_history": [
      "Xyavx"
    ],
    "last_seen": 1770814833
  },
  "6987979005": {
    "full_name": "米亚🌸 衢州鸭头 曼谷&木牌店",
    "username": "quzhouyatou7777",
    "username_history": [],
    "last_seen": 1770524945
  },
  "7464188078": {
    "full_name": "ㅤ",
    "username": "DashabiSimida",
    "username_history": [],
    "last_seen": 1770535507
  },
  "8534053561": {
    "full_name": "Davidster Mitchell8243",
    "username": "dextroexistential",
    "username_history": [],
    "last_seen": 1770537830
  },
  "8130644892": {
    "full_name": "Tara Snyder",
    "username": "Souletin_bourguig",
    "username_history": [],
    "last_seen": 1770543566
  },
  "8312481260": {
    "full_name": "Larry923 Cooper351",
    "username": "Manatee_Breezing",
    "username_history": [],
    "last_seen": 1770545551
  },
  "8333159823": {
    "full_name": "Steven Ortiz5939",
    "username": "RYcyaJ",
    "username_history": [],
    "last_seen": 1770543289
  },
  "6658486485": {
    "full_name": "西瓜🍉",
    "username": "mjb855",
    "username_history": [],
    "last_seen": 1771558714
  },
  "6707850383": {
    "full_name": "灰太狼吖",
    "username": "huitailang9526",
    "username_history": [],
    "last_seen": 1770659386
  },
  "964795921": {
    "full_name": "小梦：金铲铲大王",
    "username": "xiaoameng0",
    "username_history": [],
    "last_seen": 1770906912
  },
  "6689557679": {
    "full_name": "Boya",
    "username": "boya169",
    "username_history": [],
    "last_seen": 1770553602
  },
  "2050234148": {
    "full_name": "周百萬.（资金问题语音确认",
    "username": "BaiWanZhou",
    "username_history": [],
    "last_seen": 1771561015
  },
  "8323287194": {
    "full_name": "天天",
    "username": "mxsq861",
    "username_history": [
      "mengxiangshequ6"
    ],
    "last_seen": 1771419281
  },
  "7597955991": {
    "full_name": "Rain",
    "username": "RainfengYi",
    "username_history": [],
    "last_seen": 1770578855
  },
  "6165548313": {
    "full_name": "HR （Bode)换汇 移民局业务",
    "username": "wobode2",
    "username_history": [],
    "last_seen": 1770592579
  },
  "7611567470": {
    "full_name": "小熊冷若冰霜",
    "username": "xxiong6",
    "username_history": [],
    "last_seen": 1770781985
  },
  "6068162934": {
    "full_name": "我乐意啊！ 海外直招（不压护照，不禁足）",
    "username": "leyiii",
    "username_history": [],
    "last_seen": 1771478123
  },
  "8599285640": {
    "full_name": "Donald Diaz",
    "username": "DyslogisticRecompass",
    "username_history": [],
    "last_seen": 1770632368
  },
  "8492392926": {
    "full_name": "Busommong Blatz",
    "username": "MzcDsa",
    "username_history": [],
    "last_seen": 1770619774
  },
  "6601859663": {
    "full_name": "高进",
    "username": "GJ126888",
    "username_history": [],
    "last_seen": 1770620568
  },
  "7285250400": {
    "full_name": "木槿何溪°",
    "username": "mu457564",
    "username_history": [],
    "last_seen": 1770624998
  },
  "7726949895": {
    "full_name": "迪拜🇦🇪菜菜🥬HR🇱🇰",
    "username": "HRcaicai1",
    "username_history": [],
    "last_seen": 1770646827
  },
  "6583396126": {
    "full_name": "uu",
    "username": "UUbabby",
    "username_history": [],
    "last_seen": 1770904385
  },
  "6055301084": {
    "full_name": "贝拉🌷体育直招ing🇵🇭🇹🇭🇰🇭",
    "username": "ppbillkin88",
    "username_history": [],
    "last_seen": 1771049885
  },
  "5808393831": {
    "full_name": "冬野直招-斯里兰卡-杜拜",
    "username": "DY85692",
    "username_history": [],
    "last_seen": 1770811858
  },
  "7957383283": {
    "full_name": "富小婆",
    "username": "v777",
    "username_history": [],
    "last_seen": 1770899702
  },
  "7895396783": {
    "full_name": "伊 莉",
    "username": "lin21354",
    "username_history": [],
    "last_seen": 1770728993
  },
  "8505688056": {
    "full_name": "听云.",
    "username": "changjie86",
    "username_history": [],
    "last_seen": 1770729816
  },
  "8191955241": {
    "full_name": "小春 、（ 全地球招人 ）体育盘 。",
    "username": "xiaochun56789",
    "username_history": [],
    "last_seen": 1771513484
  },
  "1790745789": {
    "full_name": "阿乐",
    "username": "ale520",
    "username_history": [],
    "last_seen": 1770745202
  },
  "938119319": {
    "full_name": "胖头鱼（第三国身份办理）",
    "username": "xiaoyuxiaoyu1",
    "username_history": [],
    "last_seen": 1771556299
  },
  "7480225755": {
    "full_name": "HR立白(神州集团)泰国 迪拜 斯里兰卡 柬埔寨",
    "username": "xgg19",
    "username_history": [],
    "last_seen": 1770833918
  },
  "8235617209": {
    "full_name": "开云招商-老枪",
    "username": "laoqiang8868",
    "username_history": [],
    "last_seen": 1771048277
  },
  "7998447073": {
    "full_name": "绘梦",
    "username": "huimeng520",
    "username_history": [],
    "last_seen": 1770812615
  },
  "8101487136": {
    "full_name": "Richardx Kim",
    "username": "Ambsaceboredoms",
    "username_history": [],
    "last_seen": 1770887392
  },
  "1512443529": {
    "full_name": "冬野直招-斯里兰卡-杜拜",
    "username": "DY9873",
    "username_history": [],
    "last_seen": 1771050374
  },
  "5948805570": {
    "full_name": "小哥",
    "username": "Jiu_J",
    "username_history": [],
    "last_seen": 1770884174
  },
  "1990860052": {
    "full_name": "嘉尔的女朋友张张✨✨",
    "username": "FAN882",
    "username_history": [],
    "last_seen": 1770884766
  },
  "8433931372": {
    "full_name": "兰卡吴彦祖 招商导师",
    "username": "zszz888666",
    "username_history": [],
    "last_seen": 1770887690
  },
  "8209794448": {
    "full_name": "中意两不全，我选择前。",
    "username": "lqj888",
    "username_history": [],
    "last_seen": 1770923447
  },
  "7582793170": {
    "full_name": "优",
    "username": "KittyOvO555",
    "username_history": [],
    "last_seen": 1770991018
  },
  "8314087248": {
    "full_name": "Alexander Watson",
    "username": "vmwuSt",
    "username_history": [],
    "last_seen": 1770961265
  },
  "8122010568": {
    "full_name": "米粒",
    "username": "xrpoy",
    "username_history": [],
    "last_seen": 1771049691
  },
  "7663176331": {
    "full_name": "七七-宝威体育曼谷直招",
    "username": "qiooo7",
    "username_history": [],
    "last_seen": 1771466368
  },
  "6028307740": {
    "full_name": "把爱留在东南亚",
    "username": "xxinshi",
    "username_history": [],
    "last_seen": 1771392332
  },
  "6532464968": {
    "full_name": "乌萨奇（资金联系请语音确认",
    "username": "coco998865",
    "username_history": [],
    "last_seen": 1771419361
  },
  "8269104594": {
    "full_name": "Richard Garcia6167",
    "username": "aftercourseunmercifully",
    "username_history": [],
    "last_seen": 1771476878
  },
  "8530733029": {
    "full_name": "Bryan Anderson",
    "username": "PinchbackBhutia",
    "username_history": [],
    "last_seen": 1771494145
  },
  "7483769224": {
    "full_name": "大乃妹🐰（单纯好骗）",
    "username": "Ya28Eva",
    "username_history": [],
    "last_seen": 1771497982
  },
  "7208581826": {
    "full_name": "龙浩然 （关于资金来往先发裸照确认）",
    "username": "shibo221",
    "username_history": [],
    "last_seen": 1771498140
  },
  "5097760231": {
    "full_name": "15",
    "username": "xiaoliuzi6",
    "username_history": [],
    "last_seen": 1771566681
  },
  "6478997077": {
    "full_name": "不姓陈哈",
    "username": null,
    "username_history": [],
    "last_seen": 1771513059
  },
  "8526528255": {
    "full_name": "Gerald3619 Wright",
    "username": "QFTjfA",
    "username_history": [],
    "last_seen": 1771575194
  }
}